<Data version="1.0">
 <t tablelen="11" maxsize="1000">
  <pos>
   <coord x="504.11078" y="540.66852"/>
   <coord x="519.79773" y="550.7254"/>
   <coord x="514.25476" y="544.92279"/>
   <coord x="514.19879" y="544.93378"/>
   <coord x="518.75256" y="545.17682"/>
   <coord x="518.15332" y="543.73248"/>
   <coord x="503.6701" y="540.76147"/>
   <coord x="516.77161" y="539.10498"/>
   <coord x="518.15332" y="543.73248"/>
   <coord x="515.26843" y="544.28009"/>
   <coord x="510.79922" y="545.15747"/>
  </pos>
 </t>
</Data>
